vvvip/__init__.py
vvvip-0.4.0.dist-info/METADATA
vvvip-0.4.0.dist-info/WHEEL
vvvip-0.4.0.dist-info/top_level.txt
vvvip-0.4.0.dist-info/RECORD
